{"cameraMode":{"drawMode":0,"name":"Shaded","section":"Shading Mode"},"sceneLighting":false,"audioPlay":false,"sceneViewState":{"showFog":true,"showMaterialUpdate":true,"showSkybox":false,"showFlares":true,"showImageEffects":true,"showParticleSystems":true,"showVisualEffectGraphs":true,"m_FxEnabled":true},"in2DMode":false,"pivot":{"x":0.0,"y":13.410000801086426,"z":-8.449999809265137},"rotation":{"x":-0.030600447207689287,"y":0.9665659070014954,"z":-0.19592052698135377,"w":-0.1734241098165512},"size":10.0,"orthographic":false}